token_trace-0.3.2.dist-info/METADATA
token_trace-0.3.2.dist-info/WHEEL
token_trace-0.3.2.dist-info/licenses/LICENSE
token_trace/__init__.py
token_trace/app/__init__.py
token_trace/app/get_circuit.py
token_trace/app/precompute_circuits.py
token_trace/app/process_data.py
token_trace/app/run_app.py
token_trace/circuit/__init__.py
token_trace/circuit/edge_attribution.py
token_trace/circuit/node_attribution.py
token_trace/circuit/sparse_feature_circuit.py
token_trace/constants.py
token_trace/load_pretrained_model.py
token_trace/print_prompt_info.py
token_trace/sae_activation_cache.py
token_trace/sae_patcher.py
token_trace/types.py
token_trace/utils.py
token_trace-0.3.2.dist-info/RECORD
