Metadata-Version: 2.1
Name: token-trace
Version: 0.3.2
Summary: Transformer token flow visualizer
Author-Email: "Seongho Son, Liza Karmannaya, Daniel Tan, David Chanin" <chanindav@gmail.com>
License: MIT
Requires-Python: >=3.11
Requires-Dist: transformers>=4.39.3
Requires-Dist: transformer-lens>=1.15.0
Requires-Dist: sae-lens>=0.2.0
Requires-Dist: pandera>=0.18.3
Requires-Dist: streamlit>=1.33.0; extra == "client"
Requires-Dist: st-annotated-text>=4.0.1; extra == "client"
Requires-Dist: pytest>=8.1.1; extra == "client"
Requires-Dist: graphviz>=0.20.3; extra == "client"
Provides-Extra: client
